timed_batch_worker/__init__.py
timed_batch_worker/worker.py
timed_batch_worker-0.0.5.dist-info/LICENSE
timed_batch_worker-0.0.5.dist-info/METADATA
timed_batch_worker-0.0.5.dist-info/WHEEL
timed_batch_worker-0.0.5.dist-info/top_level.txt
timed_batch_worker-0.0.5.dist-info/RECORD
