Metadata-Version: 2.1
Name: timed-batch-worker
Version: 0.0.5
Summary: Python library for efficiently batch-processing workloads asynchronously with batch-size- and time-based flushes.
Home-page: https://github.com/Minibrams/timed-batch-worker
Author: Anders Brams
Author-email: anders@brams.dk
Keywords: batch,worker,asynchronous,threading,timed
Classifier: Programming Language :: Python :: 3
Classifier: License :: OSI Approved :: MIT License
Classifier: Operating System :: OS Independent
Requires-Python: >=3
License-File: LICENSE
